cdb_cellmaps/__init__.py
cdb_cellmaps/__main__.py
cdb_cellmaps/_cli_utils.py
cdb_cellmaps/_config.py
cdb_cellmaps/_data.py
cdb_cellmaps/_data_utils.py
cdb_cellmaps/_deps.py
cdb_cellmaps/_process.py
cdb_cellmaps/_raw_data.py
cdb_cellmaps/_test_utils.py
cdb_cellmaps/_utils.py
cdb_cellmaps/data.py
cdb_cellmaps/data_utils.py
cdb_cellmaps/process.py
cdb_cellmaps-0.0.1a1000208.dist-info/LICENSE.txt
cdb_cellmaps-0.0.1a1000208.dist-info/METADATA
cdb_cellmaps-0.0.1a1000208.dist-info/WHEEL
cdb_cellmaps-0.0.1a1000208.dist-info/entry_points.txt
cdb_cellmaps-0.0.1a1000208.dist-info/top_level.txt
cdb_cellmaps-0.0.1a1000208.dist-info/RECORD
